mtqdm/__init__.py
mtqdm/core.py
mtqdm/py.typed
mtqdm-0.1.4a1.dist-info/METADATA
mtqdm-0.1.4a1.dist-info/WHEEL
mtqdm-0.1.4a1.dist-info/top_level.txt
mtqdm-0.1.4a1.dist-info/RECORD
