Metadata-Version: 2.1
Name: mtqdm
Version: 0.1.4a1
Summary: Put tqdm on your menu bar.
Author: Ooj
Project-URL: homepage, https://github.com/0oj/mtqdm
Project-URL: repository, https://github.com/0oj/mtqdm
Keywords: progress,progressbar,menubar,tqdm,macos
Classifier: Environment :: MacOS X
Classifier: Operating System :: MacOS
Classifier: Programming Language :: Python :: 3.12
Classifier: Intended Audience :: Developers
Classifier: Intended Audience :: Education
Classifier: Intended Audience :: Science/Research
Requires-Python: >=3.12
Requires-Dist: rumps >=0.4.0
Requires-Dist: tqdm >=4.67.0
